[
    {
        "PRODUCTNAME": "SE2222H Dell 22 Monitor",
        "GRAPHICNAME": "SE2222H.png",
        "COST": "129.99",
        "MSRP": "129.99",
        "QTYONHAND": "3",
        "QTYONORDER": "0",
        "DESCRIPTION": "21.5inch screen, 1080p resolution with and 60Hz refresh rate. Uses HDMI",
        "BRAND": "DELL"
    },
    {
        "PRODUCTNAME": "E2222HS Dell 22 Monitor",
        "GRAPHICNAME": "E2222HS.png",
        "COST": "229.99",
        "MSRP": "229.99",
        "QTYONHAND": "1",
        "QTYONORDER": "0",
        "DESCRIPTION": "21.45inch screen, 1080p resolution with and 60Hz refresh rate. Uses HDMI",
        "BRAND": "DELL"
    },
    {
        "PRODUCTNAME": "P2222H Dell 22 Inch FHD Computer Monitor",
        "GRAPHICNAME": "P2222H.png",
        "COST": "379.99",
        "MSRP": "379.99",
        "QTYONHAND": "2",
        "QTYONORDER": "0",
        "DESCRIPTION": "22inch screen, 1080p resolution with and 60Hz refresh rate. Uses DisplayPort",
        "BRAND": "DELL"
    },
    {
        "PRODUCTNAME": "E2222H Dell 22 Monitor",
        "GRAPHICNAME": "E2222H.png",
        "COST": "219.99",
        "MSRP": "219.99",
        "QTYONHAND": "4",
        "QTYONORDER": "0",
        "DESCRIPTION": "21.45inch screen, 1080p resolution with and 60Hz refresh rate. Uses DisplayPort",
        "BRAND": "DELL"
    },
    {
        "PRODUCTNAME": "P1424H Dell 14 Inch Portable Travel Monitor",
        "GRAPHICNAME": "P1424H.png",
        "COST": "459.99",
        "MSRP": "459.99",
        "QTYONHAND": "1",
        "QTYONORDER": "0",
        "DESCRIPTION": "14inch screen, 1080p resolution with and 60Hz refresh rate. Uses DisplayPort",
        "BRAND": "DELL"
    },

    {
        "PRODUCTNAME": "AW3423DW ALIENWARE 34 CURVED QD-OLED GAMING MONITOR",
        "GRAPHICNAME": "AW3423DW.png",
        "COST": "1649.99",
        "MSRP": "1649.99",
        "QTYONHAND": "2",
        "QTYONORDER": "0",
        "DESCRIPTION": "34.18inch screen, 3440x1440 resolution with and 175Hz refresh rate. Uses DisplayPort and HDMI",
        "BRAND": "ALIENWARE"
    },
    {
        "PRODUCTNAME": "AW3821DW ALIENWARE 38 CURVED GAMING MONITOR",
        "GRAPHICNAME": "AW3821DW.png",
        "COST": "1729.99",
        "MSRP": "1729.99",
        "QTYONHAND": "1",
        "QTYONORDER": "0",
        "DESCRIPTION": "37.52inch screen, 3840x1600 resolution with and 144Hz refresh rate. Uses DisplayPort and HDMI",
        "BRAND": "ALIENWARE"
    },
    {
        "PRODUCTNAME": "AW2723DF ALIENWARE 27 GAMING MONITOR",
        "GRAPHICNAME": "AW2723DF.png",
        "COST": "829.99",
        "MSRP": "829.99",
        "QTYONHAND": "2",
        "QTYONORDER": "0",
        "DESCRIPTION": "27inch screen, 2560x1440 resolution with and 144Hz refresh rate. Uses DisplayPort and HDMI",
        "BRAND": "ALIENWARE"
    },
    {
        "PRODUCTNAME": "AW2523HF ALIENWARE 25 GAMING MONITOR",
        "GRAPHICNAME": "AW2523HF.png",
        "COST": "569.99",
        "MSRP": "569.99",
        "QTYONHAND": "5",
        "QTYONORDER": "0",
        "DESCRIPTION": "24.5inch screen, 1080p resolution with and 360Hz refresh rate. Uses DisplayPort",
        "BRAND": "ALIENWARE"
    },
    {
        "PRODUCTNAME": "AW3423DWF ALIENWARE 34 CURVED QD-OLED GAMING MONITOR",
        "GRAPHICNAME": "AW3423DWF.png",
        "COST": "1399.99",
        "MSRP": "1399.99",
        "QTYONHAND": "2",
        "QTYONORDER": "0",
        "DESCRIPTION": "34.18inch screen, 3440x1440 resolution with and 165Hz refresh rate. Uses DisplayPort and HDMI",
        "BRAND": "ALIENWARE"
    },

    {
        "PRODUCTNAME": "G25-10 Lenovo 24.5 inch NVIDIA G-SYNC Gaming Monitor",
        "GRAPHICNAME": "G25-10.png",
        "COST": "339.99",
        "MSRP": "339.99",
        "QTYONHAND": "0",
        "QTYONORDER": "0",
        "DESCRIPTION": "24.5inch screen, 1980x1080 resolution with and 144Hz refresh rate. Uses DisplayPort and HDMI",
        "BRAND": "LENOVO"
    },
    {
        "PRODUCTNAME": "G24e-20 Lenovo 23.8 inch Gaming Monitor",
        "GRAPHICNAME": "G24e-20.png",
        "COST": "269.99",
        "MSRP": "269.99",
        "QTYONHAND": "1",
        "QTYONORDER": "0",
        "DESCRIPTION": "23.8inch screen, 1980x1080 resolution with and 100Hz refresh rate. Uses DisplayPort and HDMI",
        "BRAND": "LENOVO"
    },
    {
        "PRODUCTNAME": "Y27q-20 Lenovo Legion 27 inch NVIDIA G-SYNC Gaming Monitor",
        "GRAPHICNAME": "Y27q-20.png",
        "COST": "649.99",
        "MSRP": "649.99",
        "QTYONHAND": "6",
        "QTYONORDER": "0",
        "DESCRIPTION": "27inch screen, 2560x1440 resolution with and 165Hz refresh rate. Uses DisplayPort and HDMI",
        "BRAND": "LENOVO"
    },
    {
        "PRODUCTNAME": "G32qc-10 Lenovo 31.5 inch Curved Gaming Monitor",
        "GRAPHICNAME": "G32qc-10.png",
        "COST": "479.99",
        "MSRP": "479.99",
        "QTYONHAND": "2",
        "QTYONORDER": "0",
        "DESCRIPTION": "31.5inch screen, 2560x1440 resolution with and 144Hz refresh rate. Uses DisplayPort and HDMI",
        "BRAND": "LENOVO"
    },
    {
        "PRODUCTNAME": "G27-30 Lenovo 27 inch FHD Gaming Monitor",
        "GRAPHICNAME": "G27-30.png",
        "COST": "339.99",
        "MSRP": "339.99",
        "QTYONHAND": "3",
        "QTYONORDER": "0",
        "DESCRIPTION": "27inch screen, 2560x1440 resolution with and 165Hz refresh rate. Uses HDMI",
        "BRAND": "LENOVO"
    }
]
